setup.py
json_rest/__init__.py
json_rest/__version__.py
json_rest/exceptions.py
json_rest/logging_utils.py
json_rest/no_data.py
json_rest/raw.py
json_rest/sender.py
json_rest.egg-info/PKG-INFO
json_rest.egg-info/SOURCES.txt
json_rest.egg-info/dependency_links.txt
json_rest.egg-info/requires.txt
json_rest.egg-info/top_level.txt